{
  "pensamento": [
    {
      "id": 1,
      "conteudo": "Novo pensamento 1. Editando o pensamento 1",
      "autoria": "eu mesmo",
      "modelo": "modelo3"
    },
    {
      "id": 3,
      "conteudo": "Santa maria MÃE de Deus",
      "autoria": "eu mesmo",
      "modelo": "modelo1"
    },
    {
      "conteudo": "Novo pensamento testeNovo pensame",
      "autoria": "Henrique",
      "modelo": "modelo1",
      "id": 5
    },
    {
      "conteudo": "Infelizmente tem que ir trabalhar",
      "autoria": "henrique",
      "modelo": "modelo3",
      "id": 6
    },
    {
      "conteudo": "Preciso comprar um celular novo que seja barato e bãão",
      "autoria": "Henrique",
      "modelo": "modelo2",
      "id": 7
    }
  ]
}